holded/__init__.py
holded/async_client.py
holded/client.py
holded/exceptions.py
holded/models/__init__.py
holded/models/accounting.py
holded/models/base.py
holded/models/contacts.py
holded/models/crm.py
holded/models/documents.py
holded/models/employees.py
holded/models/expense_accounts.py
holded/models/numbering_series.py
holded/models/products.py
holded/models/projects.py
holded/models/remittances.py
holded/models/sales_channels.py
holded/models/treasury.py
holded/models/warehouse.py
holded/resources/__init__.py
holded/resources/accounting.py
holded/resources/async_accounting.py
holded/resources/async_contacts.py
holded/resources/async_crm.py
holded/resources/async_documents.py
holded/resources/async_employees.py
holded/resources/async_expense_accounts.py
holded/resources/async_numbering_series.py
holded/resources/async_products.py
holded/resources/async_projects.py
holded/resources/async_remittances.py
holded/resources/async_sales_channels.py
holded/resources/async_treasury.py
holded/resources/async_warehouse.py
holded/resources/contacts.py
holded/resources/crm.py
holded/resources/documents.py
holded/resources/employees.py
holded/resources/expense_accounts.py
holded/resources/numbering_series.py
holded/resources/products.py
holded/resources/projects.py
holded/resources/remittances.py
holded/resources/sales_channels.py
holded/resources/treasury.py
holded/resources/warehouse.py
holded_python-0.1.3.dist-info/LICENSE
holded_python-0.1.3.dist-info/METADATA
holded_python-0.1.3.dist-info/WHEEL
holded_python-0.1.3.dist-info/top_level.txt
holded_python-0.1.3.dist-info/RECORD
